wfetch/main.py
wfetch_cli-0.1.0.dist-info/METADATA
wfetch_cli-0.1.0.dist-info/WHEEL
wfetch_cli-0.1.0.dist-info/entry_points.txt
wfetch_cli-0.1.0.dist-info/RECORD
