Metadata-Version: 2.1
Name: wfetch-cli
Version: 0.1.0
Summary: A tool that can download files and verify their checksum on the fly.
Author: Bohdan Vanieiev
Author-email: bohdan.vanieiev@aptiv.com
Requires-Python: >=3.7,<4.0
Classifier: Programming Language :: Python :: 3
Classifier: Programming Language :: Python :: 3.7
Classifier: Programming Language :: Python :: 3.8
Classifier: Programming Language :: Python :: 3.9
Classifier: Programming Language :: Python :: 3.10
Classifier: Programming Language :: Python :: 3.11
Requires-Dist: requests (>=2.30.0,<3.0.0)
Requires-Dist: tqdm (>=4.65.0,<5.0.0)
